Mux/MuxL2/probadormux_L2.v
module probador2to1( 
	output reg  clk,
	output reg  clk_2f,
	output reg  clk_4f,
	output reg selector,
	output reg		reset_L,
	output reg [7:0] 	in0,
	output reg [7:0] 	in1,
	//output reg [7:0] 	in2,
	//output reg [7:0] 	in3,
	output reg 		valid_bit0,
	output reg 		valid_bit1,
	//output reg 		valid_bit2,
	//output reg 		valid_bit3,
	input 			valid_bit_out1,
	input 			valid_bit_out2,
	//input 			validyosys1,
	//input 			validyosys2,
	input [7:0] 		data_out1,
	input [7:0] 		data_out2
	//input [7:0] 		data_outyosys1,
	//input [7:0] 		data_outyosys2
	);


	initial begin
		$dumpfile("mux2to1_L2.vcd");
		$dumpvars;		


		reset_L= 0;
		valid_bit0 <= 1;
		valid_bit1 <= 1;
		//valid_bit2 <= 1;
		//valid_bit3 <= 1;
		in0 <= 'b0;
		in1 <= 'b0;
		//in2 <= 'b0;
		//in3 <= 'b0;
		selector =1;
		repeat (1)
		@(posedge clk_4f);
		reset_L <= 1;
		@(posedge clk_4f);
		in0 <= 1;
		in1 <= 2;
		//in2 <= 3;
		//in3 <= 4;
		@(posedge clk_4f);
		in0 <= 'hA;
		in1 <= 'hB;
		//in2 <= 'hc;
		//in3 <= 'hD;
		@(posedge clk_4f);
		in0 <= 5;
		in1 <= 6;
		//in2 <= 7;
		//in3 <= 8;
		@(posedge clk_4f);
		in0 <= 'hFF;
		in1 <= 'hAA;
		//in2 <= 'hBB;
		//in3 <= 'hCC;
		@(posedge clk_4f);
		in0 <= 9;
		in1 <= 1;
		//in2 <= 6;
		//in3 <= 7;
		@(posedge clk_4f);
		in0 <= 'hF1;
		in1 <= 'hA2;
		//in2 <= 'hB3;
		//in3 <= 'hC5;
		repeat (1) begin
    @(posedge clk);
    end
		$finish;	
	end
	// Reloj
	initial	clk <= 0;
	always	#300 clk <= ~clk;
	initial clk_2f 	<= 1;
	always	#150 clk_2f 	<= ~clk_2f;
	initial clk_4f 	<= 1;
	always	#75 clk_4f 	<= ~clk_4f;
endmodule

Phy/Mux2a1_cuatrobits.v
module mux_conductual(
	input selector,
	input reset_L,
	input [3:0] in0,
	input [3:0] in1,
	input valid_bit0,
	input valid_bit1,
	output reg valid_bit_out,
	output reg [3:0] data_out
	);
	reg [3:0] A;
	reg validotemporal;
	always @(*) begin
	A = 4'b00; 
	validotemporal = 0;

		if (selector==0) 
		begin
			//validotemporal = valid_bit0;
			validotemporal = 1;
			if (valid_bit0)
				A = in0;
			else
				A = 4'b00;

		end

		else begin
			//validotemporal = valid_bit1;
			validotemporal = 1;
			if (valid_bit1)
				A = in1;
			else
				A = 4'b00;
		end

	end

	always @ (*) begin
		valid_bit_out<=validotemporal;
		if (reset_L==0)
			data_out <= 4'b00;
		else
			data_out <= A;
	end
endmodule

Mux/MuxL1/Mux2a1_ochobits.v
`include "Mux2a1_cuatrobits.v"
module  mux_2to1_4bits (
	input selector,
	input reset_L,
	input [7:0] in0,
	input [7:0] in1,
	input valid_bit0,
	input valid_bit1,
	output wire valid_bit_out,
	output wire [7:0] data_out
	);
	wire bittemporal;
  	mux_conductual  mux1 (selector,reset_L,in0[3:0],in1[3:0],valid_bit0,valid_bit1,valid_bit_out,data_out[3:0]);
	mux_conductual  mux2 (selector,reset_L,in0[7:4],in1[7:4],valid_bit0,valid_bit1,bittemporal,data_out[7:4]);
endmodule

Mux/MuxL2/Mux2a1_descp_condL2.v
`include "Mux2a1_ochobits.v"
module mux2to1_L2 (
	input clk_4f,
	input selector,
	input reset_L,
	input [7:0] in0,
	input [7:0] in1,
	input valid_bit0,
	input valid_bit1,
	output wire valid_bit_out1,
	output wire [7:0] data_out1
	);
	/*wire valid_bit_mux1;
	wire valid_bit_mux2;
	wire [7:0] outMux1;
	wire [7:0] outMux2;*/
	//Logica para L1: MUX DE 2 A 1
  	mux_2to1_4bits  mux1_L2(clk_4f,reset_L,in0[7:0],in1[7:0],valid_bit0,valid_bit1,valid_bit_out1,data_out1[7:0]);
endmodule

Mux/MuxL2/testbench2to1.v
`timescale 	1ns	/ 100ps
`include "Mux2a1_descp_condL2.v"
`include "probadormux_L2.v"
module bancoPruebas;

    wire clk, clk_2f,clk_4f,reset_L,valid_bit0,valid_bit1,valid_bit2,valid_bit3, valid_bit_out1, valid_bit_out2;
    wire selector;
    wire [7:0] in0;
    wire [7:0] in1;
    wire [7:0] in2;
    wire [7:0] in3;
    wire [7:0] data_out1;
    wire [7:0] data_out2;
    //wire [7:0] data_outyosys1;
    //wire [7:0] data_outyosys2;
  	mux2to1_L2 muxpruebaL2(/*AUTOINST*/
			   // Outputs
			   .valid_bit_out1	(valid_bit_out1),
			   //.valid_bit_out2	(valid_bit_out2),
			   .data_out1		(data_out1[7:0]),
			   //.data_out2		(data_out2[7:0]),
			   // Inputs
			   .clk_4f		(clk_4f),
			   .selector	(selector),
			   .reset_L		(reset_L),
			   .in0			(in0[7:0]),
			   .in1			(in1[7:0]),
         	//	   .in2			(in2[7:0]),
			//   .in3			(in3[7:0]),
			   .valid_bit0		(valid_bit0),
         		   .valid_bit1		(valid_bit1)
         	//	   .valid_bit2		(valid_bit2),
         	//	   .valid_bit3		(valid_bit3)
			 );
   //mux_4to1_Estruct mux_yosys(/*AUTOINST*/
			   /*// Outputs
			   .valid_bit_out1		(validyosys),
			   //.valid_bit_out2		(validyosys),
			   .data_out1		(data_outyosys[7:0]),
			   // Inputs
			   .clk			(clk),
			   .selector		(selector),
			   .reset_L		(reset_L),
			   .in0			(in0[7:0]),
			   .in1			(in1[7:0]),
        		   .in2			(in2[7:0]),
			   .in3			(in3[7:0]),
			   .valid_bit0		(valid_bit0),
			   .valid_bit1		(valid_bit1),
			   .valid_bit2		(valid_bit2),
			   .valid_bit3		(valid_bit3));*/

			   // Outputs
	//		   .valid_bit_out1	(validyosys1),
	//		   .valid_bit_out2	(validyosys2),
	//		   .data_out1		(data_outyosys1[7:0]),
	//		   .data_out2		(data_outyosys2[7:0]),
			   // Inputs
	//		   .clk			(clk),
	//		   .clk_2f		(clk_2f),
	//		   .selector	(selector),
	//		   .reset_L		(reset_L),
	//		   .in0			(in0[7:0]),
	//		   .in1			(in1[7:0]),
    //   		   .in2			(in2[7:0]),
	//		   .in3			(in3[7:0]),
	//		   .valid_bit0		(valid_bit0),
    //   		   .valid_bit1		(valid_bit1),
    //     		   .valid_bit2		(valid_bit2),
    //     		   .valid_bit3		(valid_bit3));

   probador2to1 mux_probL2(/*AUTOINST*/
		     // Outputs
		     .clk		(clk),
		     .clk_2f		(clk_2f),
			 .clk_4f		(clk_4f),
		     .selector	(selector),
		     .reset_L		(reset_L),
		     .in0		(in0[7:0]),
		     .in1		(in1[7:0]),
         	 //    .in2		(in2[7:0]),
		     //.in3		(in3[7:0]),
         	     .valid_bit0		(valid_bit0),
         	     .valid_bit1		(valid_bit1),
         	     //.valid_bit2		(valid_bit2),
         	     //.valid_bit3		(valid_bit3),

		     // Inputs
		     .valid_bit_out1		(valid_bit_out1),
		     //.valid_bit_out2		(valid_out2),
		     .data_out1			(data_out1[7:0])
		     //.data_out2			(data_out2[7:0])
			   //.validyosys1	(validyosys1),
			   //.validyosys2	(validyosys2),
			   //.data_outyosys1		(data_outyosys1[7:0]),
			   //.data_outyosys2		(data_outyosys2[7:0])
			   );
endmodule

Mux/MuxL2/mux2to1_L2.vcd
$date
	Wed May 27 12:44:19 2020
$end
$version
	Icarus Verilog
$end
$timescale
	100ps
$end
$scope module bancoPruebas $end
$var wire 1 ! valid_bit_out1 $end
$var wire 1 " valid_bit1 $end
$var wire 1 # valid_bit0 $end
$var wire 1 $ selector $end
$var wire 1 % reset_L $end
$var wire 8 & in1 [7:0] $end
$var wire 8 ' in0 [7:0] $end
$var wire 8 ( data_out1 [7:0] $end
$var wire 1 ) clk_4f $end
$var wire 1 * clk_2f $end
$var wire 1 + clk $end
$scope module mux_probL2 $end
$var wire 8 , data_out2 [7:0] $end
$var wire 1 - valid_bit_out2 $end
$var wire 1 ! valid_bit_out1 $end
$var wire 8 . data_out1 [7:0] $end
$var reg 1 + clk $end
$var reg 1 * clk_2f $end
$var reg 1 ) clk_4f $end
$var reg 8 / in0 [7:0] $end
$var reg 8 0 in1 [7:0] $end
$var reg 1 % reset_L $end
$var reg 1 $ selector $end
$var reg 1 # valid_bit0 $end
$var reg 1 " valid_bit1 $end
$upscope $end
$scope module muxpruebaL2 $end
$var wire 1 ) clk_4f $end
$var wire 8 1 in0 [7:0] $end
$var wire 8 2 in1 [7:0] $end
$var wire 1 % reset_L $end
$var wire 1 $ selector $end
$var wire 1 # valid_bit0 $end
$var wire 1 " valid_bit1 $end
$var wire 1 ! valid_bit_out1 $end
$var wire 8 3 data_out1 [7:0] $end
$scope module mux1_L2 $end
$var wire 8 4 in0 [7:0] $end
$var wire 8 5 in1 [7:0] $end
$var wire 1 % reset_L $end
$var wire 1 ) selector $end
$var wire 1 # valid_bit0 $end
$var wire 1 " valid_bit1 $end
$var wire 1 ! valid_bit_out $end
$var wire 8 6 data_out [7:0] $end
$var wire 1 7 bittemporal $end
$scope module mux1 $end
$var wire 4 8 in0 [3:0] $end
$var wire 4 9 in1 [3:0] $end
$var wire 1 % reset_L $end
$var wire 1 ) selector $end
$var wire 1 # valid_bit0 $end
$var wire 1 " valid_bit1 $end
$var reg 4 : A [3:0] $end
$var reg 4 ; data_out [3:0] $end
$var reg 1 ! valid_bit_out $end
$var reg 1 < validotemporal $end
$upscope $end
$scope module mux2 $end
$var wire 4 = in0 [3:0] $end
$var wire 4 > in1 [3:0] $end
$var wire 1 % reset_L $end
$var wire 1 ) selector $end
$var wire 1 # valid_bit0 $end
$var wire 1 " valid_bit1 $end
$var reg 4 ? A [3:0] $end
$var reg 4 @ data_out [3:0] $end
$var reg 1 7 valid_bit_out $end
$var reg 1 A validotemporal $end
$upscope $end
$upscope $end
$upscope $end
$upscope $end
$enddefinitions $end
#0
$dumpvars
1A
b0 @
b0 ?
b0 >
b0 =
1<
b0 ;
b0 :
b0 9
b0 8
17
b0 6
b0 5
b0 4
b0 3
b0 2
b0 1
b0 0
b0 /
b0 .
z-
bz ,
0+
1*
1)
b0 (
b0 '
b0 &
1%
1$
1#
1"
1!
$end
#750
1<
1A
0)
#1500
b10 (
b10 .
b10 3
b10 6
b10 ;
b10 :
b10 9
b1 8
b10 &
b10 0
b10 2
b10 5
b1 '
b1 /
b1 1
b1 4
1<
1A
1)
0*
#2250
b1 (
b1 .
b1 3
b1 6
b1 ;
1<
b1 :
1A
0)
#3000
b1011 9
b1010 8
b1011 (
b1011 .
b1011 3
b1011 6
b1011 ;
b1011 &
b1011 0
b1011 2
b1011 5
b1010 '
b1010 /
b1010 1
b1010 4
1<
b1011 :
1A
1)
1*
1+
#3750
b1010 (
b1010 .
b1010 3
b1010 6
b1010 ;
1<
b1010 :
1A
0)
#4500
b110 9
b101 8
b110 (
b110 .
b110 3
b110 6
b110 ;
b110 &
b110 0
b110 2
b110 5
b101 '
b101 /
b101 1
b101 4
1<
b110 :
1A
1)
0*
#5250
b101 (
b101 .
b101 3
b101 6
b101 ;
1<
b101 :
1A
0)
#6000
b1010 @
b1010 ?
b1010 9
b1010 >
b1111 8
b1111 =
b10101010 (
b10101010 .
b10101010 3
b10101010 6
b1010 ;
b10101010 &
b10101010 0
b10101010 2
b10101010 5
b11111111 '
b11111111 /
b11111111 1
b11111111 4
1<
b1010 :
1A
1)
1*
0+
#6750
b1111 ;
b11111111 (
b11111111 .
b11111111 3
b11111111 6
b1111 @
1<
b1111 :
1A
b1111 ?
0)
#7500
b1 9
b0 >
b1001 8
b0 =
b1 ;
b1 (
b1 .
b1 3
b1 6
b0 @
b1 &
b1 0
b1 2
b1 5
b1001 '
b1001 /
b1001 1
b1001 4
1<
b1 :
1A
b0 ?
1)
0*
#8250
b1001 (
b1001 .
b1001 3
b1001 6
b1001 ;
1<
b1001 :
1A
0)
#9000
b1010 @
b1010 ?
b10 9
b1010 >
b1 8
b1111 =
b10100010 (
b10100010 .
b10100010 3
b10100010 6
b10 ;
b10100010 &
b10100010 0
b10100010 2
b10100010 5
b11110001 '
b11110001 /
b11110001 1
b11110001 4
1<
b10 :
1A
1)
1*
1+
#9750
b1 ;
b11110001 (
b11110001 .
b11110001 3
b11110001 6
b1111 @
1<
b1 :
1A
b1111 ?
0)
#10500
b10 ;
b10100010 (
b10100010 .
b10100010 3
b10100010 6
b1010 @
1<
b10 :
1A
b1010 ?
1)
0*
#11250
b1 ;
b11110001 (
b11110001 .
b11110001 3
b11110001 6
b1111 @
1<
b1 :
1A
b1111 ?
0)
#12000
b10 ;
b10100010 (
b10100010 .
b10100010 3
b10100010 6
b1010 @
1<
b10 :
1A
b1010 ?
1)
1*
0+
#12750
b1 ;
b11110001 (
b11110001 .
b11110001 3
b11110001 6
b1111 @
1<
b1 :
1A
b1111 ?
0)
#13500
b10 ;
b10100010 (
b10100010 .
b10100010 3
b10100010 6
b1010 @
1<
b10 :
1A
b1010 ?
1)
0*
#14250
b1 ;
b11110001 (
b11110001 .
b11110001 3
b11110001 6
b1111 @
1<
b1 :
1A
b1111 ?
0)
#15000
b10 ;
b10100010 (
b10100010 .
b10100010 3
b10100010 6
b1010 @
1<
b10 :
1A
b1010 ?
1)
1*
1+
