Demux/DemuxL2/probadordemux_L2.v
module probadordemuxL2( 
     //entradas
	output reg clk_2f,
	output reg clk,
    output reg clk_4f,
    output reg reset_L,
    output reg selectorL2,
    output reg valid,
    output reg [7:0] data_in0_demuxL2,   
    //salidas
    input validout0,
    input validout1,
    input [7:0] dataout0_demuxL2,
    input [7:0] dataout1_demuxL2
    );


	initial begin
		$dumpfile("demux1a2L2.vcd");
		$dumpvars;		
		reset_L= 0;
		valid <= 1;
		data_in0_demuxL2 <= 'b0;
		selectorL2 = 1;
		@(posedge clk_4f);
		@(posedge clk_4f);
		reset_L <= 1;
		@(posedge clk_4f);
        valid <= 0;
		data_in0_demuxL2 <= data_in0_demuxL2 + 16;
			
        @(posedge clk_4f);
		valid <= 1;
		data_in0_demuxL2 <= data_in0_demuxL2 + 2;
		@(posedge clk_4f);

		data_in0_demuxL2 <= 'hA;
		@(posedge clk_4f);
		valid <= 1;
		data_in0_demuxL2 <= data_in0_demuxL2 + 10;
		@(posedge clk_4f);
		valid <= 0;
		data_in0_demuxL2 <= data_in0_demuxL2 + 8;
		repeat (1) begin
            @(posedge clk);
        end
		$finish;	
	end
	// Reloj
	initial	clk <= 0;
	always	#300 clk <= ~clk;
	initial clk_2f 	<= 1;
	always	#150 clk_2f 	<= ~clk_2f;
    initial clk_4f 	<= 1;
	always	#75 clk_4f 	<= ~clk_4f;



endmodule

Demux/DemuxL2/Demux1a2_cuatrobits.v
module demux1a2dosbits_descp_cond (
    //entradas
    input reset_L,
    input selector,
    input valid,
    input [3:0] data_in,
    //salidas
    output reg validout0,
    output reg validout1,
    output reg [3:0] dataout_demux1a2dosbits0,
    output reg [3:0] dataout_demux1a2dosbits1
    );
    reg [3:0] temp1, temp2;
    always @ (*) begin
        temp1 = 0;
        temp2 = 0;
        if (selector == 1) begin
            temp1 = data_in;
            validout1 = valid;
            validout0 = validout0;
        end    
        else begin
            temp1 = data_in;
            validout0 = valid;
            validout1 = validout1;
        end
    end
    always @ (*) begin
        if(valid == 1)
            temp2 = temp1;
        else
            temp2 = 4'b00;
    end
    always @ (*) begin
        if(reset_L == 0) begin
            dataout_demux1a2dosbits0 = 4'b0;
            dataout_demux1a2dosbits1 = 4'b0;
            validout0 = 0;
            validout1 = 0;
        end    
        else begin
            if(selector == 1) begin 
                dataout_demux1a2dosbits1 = temp2;
                dataout_demux1a2dosbits0 = dataout_demux1a2dosbits0;
            end
            else begin
                dataout_demux1a2dosbits0 = temp2;
                dataout_demux1a2dosbits1 = dataout_demux1a2dosbits1;
            end 
        end
    end
endmodule

Demux/DemuxL2/Demux1a2_ochobits.v
`include  "Demux1a2_cuatrobits.v"
module demux1a2ochobits_descp_cond(
    //entradas
    input reset_L,
    input selector,
    input valid,
    input [7:0] data_in,
    //salidas
    output wire validout0,
    output wire validout1,
    output wire [7:0] dataout_demux1a2dosbits0,
    output wire [7:0] dataout_demux1a2dosbits1
);
    wire temp0, temp1;
    demux1a2dosbits_descp_cond demux1a2ochobits_uno(reset_L,selector,valid,data_in[3:0],validout0,validout1,dataout_demux1a2dosbits0[3:0],dataout_demux1a2dosbits1[3:0]);
    demux1a2dosbits_descp_cond demux1a2ochobits_dos(reset_L,selector,valid,data_in[7:4],temp0,temp1,dataout_demux1a2dosbits0[7:4],dataout_demux1a2dosbits1[7:4]);
   
endmodule

Demux/DemuxL2/Demux1a2_descp_condL2.v
`include "Demux1a2_ochobits.v"
module demux2a1_descp_condL2(
     //entradas
    input clk_2f,
    input reset_L,
    input selectorL2,
    input valid,
    input [7:0] data_in0_demuxL2,   
    //salidas
    output wire validout0,
    output wire validout1,
    output wire [7:0] dataout0_demuxL2,
    output wire [7:0] dataout1_demuxL2
);
    demux1a2ochobits_descp_cond demux1a2_8bitunoL2(reset_L,clk_2f,valid,data_in0_demuxL2,validout0,validout1,dataout0_demuxL2,dataout1_demuxL2);
endmodule

Demux/DemuxL2/BancoPruebasL2.v
`timescale 	1ns	/ 100ps
`include "Demux1a2_descp_condL2.v"
`include "probadordemux_L2.v" 
module BancoPruebasDemuxL2; 
    //entradas
    wire clk_2f;
	wire clk;
    wire clk_4f;
    wire reset_L;
    wire selectorL2;
    wire valid;
    wire [7:0] data_in0_demuxL2;   
    //salidas
    wire validout0;
    wire validout1;
    wire [7:0] dataout0_demuxL2;
    wire [7:0] dataout1_demuxL2;
    demux2a1_descp_condL2 demuxL2(     
                //entradas
                .clk_2f (clk_2f),
                .reset_L (reset_L),
                .selectorL2 (selectorL2),
                .valid (valid),
                .data_in0_demuxL2 (data_in0_demuxL2),   
                //salidas
                .validout0 (validout0),
                .validout1 (validout1),
                .dataout0_demuxL2 (dataout0_demuxL2),
                .dataout1_demuxL2 (dataout1_demuxL2)
    );

    probadordemuxL2 prueba(
                //entradas
                .clk_2f (clk_2f),
                .clk (clk),
                .clk_4f (clk_4f),
                .reset_L (reset_L),
                .selectorL2 (selectorL2),
                .valid (valid),
                .data_in0_demuxL2 (data_in0_demuxL2),   
                //salidas
                .validout0 (validout0),
                .validout1 (validout1),
                .dataout0_demuxL2 (dataout0_demuxL2),
                .dataout1_demuxL2 (dataout1_demuxL2)


    );
endmodule

Demux/DemuxL2/demux1a2L2.vcd
$date
	Wed May 27 12:26:51 2020
$end
$version
	Icarus Verilog
$end
$timescale
	100ps
$end
$scope module BancoPruebasDemuxL2 $end
$var wire 1 ! validout1 $end
$var wire 1 " validout0 $end
$var wire 1 # valid $end
$var wire 1 $ selectorL2 $end
$var wire 1 % reset_L $end
$var wire 8 & dataout1_demuxL2 [7:0] $end
$var wire 8 ' dataout0_demuxL2 [7:0] $end
$var wire 8 ( data_in0_demuxL2 [7:0] $end
$var wire 1 ) clk_4f $end
$var wire 1 * clk_2f $end
$var wire 1 + clk $end
$scope module demuxL2 $end
$var wire 1 ! validout1 $end
$var wire 1 " validout0 $end
$var wire 1 # valid $end
$var wire 1 $ selectorL2 $end
$var wire 1 % reset_L $end
$var wire 8 , dataout1_demuxL2 [7:0] $end
$var wire 8 - dataout0_demuxL2 [7:0] $end
$var wire 8 . data_in0_demuxL2 [7:0] $end
$var wire 1 * clk_2f $end
$scope module demux1a2_8bitunoL2 $end
$var wire 1 ! validout1 $end
$var wire 1 " validout0 $end
$var wire 1 # valid $end
$var wire 1 / temp1 $end
$var wire 1 0 temp0 $end
$var wire 1 * selector $end
$var wire 1 % reset_L $end
$var wire 8 1 dataout_demux1a2dosbits1 [7:0] $end
$var wire 8 2 dataout_demux1a2dosbits0 [7:0] $end
$var wire 8 3 data_in [7:0] $end
$scope module demux1a2ochobits_dos $end
$var wire 4 4 data_in [3:0] $end
$var wire 1 # valid $end
$var wire 1 * selector $end
$var wire 1 % reset_L $end
$var reg 4 5 dataout_demux1a2dosbits0 [3:0] $end
$var reg 4 6 dataout_demux1a2dosbits1 [3:0] $end
$var reg 4 7 temp1 [3:0] $end
$var reg 4 8 temp2 [3:0] $end
$var reg 1 0 validout0 $end
$var reg 1 / validout1 $end
$upscope $end
$scope module demux1a2ochobits_uno $end
$var wire 4 9 data_in [3:0] $end
$var wire 1 # valid $end
$var wire 1 * selector $end
$var wire 1 % reset_L $end
$var reg 4 : dataout_demux1a2dosbits0 [3:0] $end
$var reg 4 ; dataout_demux1a2dosbits1 [3:0] $end
$var reg 4 < temp1 [3:0] $end
$var reg 4 = temp2 [3:0] $end
$var reg 1 " validout0 $end
$var reg 1 ! validout1 $end
$upscope $end
$upscope $end
$upscope $end
$scope module prueba $end
$var wire 8 > dataout0_demuxL2 [7:0] $end
$var wire 8 ? dataout1_demuxL2 [7:0] $end
$var wire 1 " validout0 $end
$var wire 1 ! validout1 $end
$var reg 1 + clk $end
$var reg 1 * clk_2f $end
$var reg 1 ) clk_4f $end
$var reg 8 @ data_in0_demuxL2 [7:0] $end
$var reg 1 % reset_L $end
$var reg 1 $ selectorL2 $end
$var reg 1 # valid $end
$upscope $end
$upscope $end
$enddefinitions $end
#0
$dumpvars
b0 @
b0 ?
b0 >
b0 =
b0 <
b0 ;
b0 :
b0 9
b0 8
b0 7
b0 6
b0 5
b0 4
b0 3
b0 2
b0 1
00
1/
b0 .
b0 -
b0 ,
0+
1*
1)
b0 (
b0 '
b0 &
0%
1$
1#
0"
1!
$end
#750
0)
#1500
1%
0/
10
0!
1"
1)
0*
#2250
0)
#3000
b1 7
b1 4
b10000 (
b10000 .
b10000 3
b10000 @
0#
0/
0!
1)
1*
1+
#3750
0)
#4500
b10 :
b10 =
b10 <
b10010 '
b10010 -
b10010 2
b10010 >
b1 5
b10 9
b1 8
b10010 (
b10010 .
b10010 3
b10010 @
1#
10
b1 7
1"
1)
0*
#5250
0)
#6000
b0 4
b1010 9
b1010 (
b1010 .
b1010 3
b1010 @
b0 6
b1010 &
b1010 ,
b1010 1
b1010 ?
b1010 ;
1/
b0 8
b0 7
1!
b1010 =
b1010 <
1)
1*
0+
#6750
0)
#7500
b1 8
b1 7
b1 4
b100 9
b10100 (
b10100 .
b10100 3
b10100 @
b1 5
b10100 '
b10100 -
b10100 2
b10100 >
b100 :
b100 =
b100 <
1)
0*
#8250
0)
#9000
b1100 9
0/
0!
b11100 (
b11100 .
b11100 3
b11100 @
0#
b0 6
b0 8
b1 7
b0 &
b0 ,
b0 1
b0 ?
b0 ;
b0 =
b1100 <
1)
1*
1+
#9750
0)
#10500
b0 5
00
b1 7
b0 '
b0 -
b0 2
b0 >
b0 :
0"
b1100 <
1)
0*
#11250
0)
#12000
b1 7
b1100 <
1)
1*
0+
#12750
0)
#13500
b1 7
b1100 <
1)
0*
#14250
0)
#15000
b1 7
b1100 <
1)
1*
1+
